AUTHORS.rst
CONTRIBUTING.rst
HISTORY.rst
LICENSE
MANIFEST.in
README.rst
requirements.txt
setup.cfg
setup.py
docs/Makefile
docs/authors.rst
docs/conf.py
docs/contributing.rst
docs/history.rst
docs/index.rst
docs/installation.rst
docs/make.bat
docs/readme.rst
docs/usage.rst
loganalyzer/__init__.py
loganalyzer/cli.py
loganalyzer/loganalyzer.py
loganalyzer.egg-info/PKG-INFO
loganalyzer.egg-info/SOURCES.txt
loganalyzer.egg-info/dependency_links.txt
loganalyzer.egg-info/entry_points.txt
loganalyzer.egg-info/not-zip-safe
loganalyzer.egg-info/requires.txt
loganalyzer.egg-info/top_level.txt
tests/errors.log
tests/info.log
tests/system.log
tests/test_loganalyzer.py
tests/test_server.py