Metadata-Version: 1.1
Name: loganalyzer
Version: 0.1.2
Summary: Collect and analyze log from multiples sources
Home-page: https://github.com/asteriogonzalez/loganalyzer
Author: Asterio
Author-email: asterio.gonzalez@gmail.com
License: MIT license
Keywords: loganalyzer
Platform: UNKNOWN
Classifier: Development Status :: 2 - Pre-Alpha
Classifier: Intended Audience :: Developers
Classifier: License :: OSI Approved :: MIT License
Classifier: Natural Language :: English
Classifier: Programming Language :: Python :: 2
Classifier: Programming Language :: Python :: 2.7
Classifier: Programming Language :: Python :: 3
Classifier: Programming Language :: Python :: 3.4
Classifier: Programming Language :: Python :: 3.5
Classifier: Programming Language :: Python :: 3.6
Classifier: Programming Language :: Python :: 3.7
